fortitude/__init__.py
fortitude/__main__.py
fortitude/default_page.py
fortitude-0.1.9.12.dist-info/METADATA
fortitude-0.1.9.12.dist-info/WHEEL
fortitude-0.1.9.12.dist-info/top_level.txt
fortitude-0.1.9.12.dist-info/RECORD
