Metadata-Version: 2.4
Name: fortitude
Version: 0.1.9.12
Summary: Smart Odoo Loadbalancer
License: GPL V3
Requires-Dist: websocket-client==1.7.0
Requires-Dist: requests==2.31.0
Dynamic: description
Dynamic: description-content-type
Dynamic: license
Dynamic: requires-dist
Dynamic: summary
